slurmer/__init__.py
slurmer/task_runner.py
slurmer-1.0.7.dist-info/LICENSE
slurmer-1.0.7.dist-info/WHEEL
slurmer-1.0.7.dist-info/METADATA
slurmer-1.0.7.dist-info/RECORD
