Metadata-Version: 2.1
Name: slurmer
Version: 1.0.7
Summary: A package to schedule different tasks in parallel with cluster support.
Home-page: https://jmigual.github.io/slurmer/
License: MIT
Author: Joan Marcè i Igual
Author-email: J.Marce.i.Igual@tue.nl
Requires-Python: >=3.10,<4.0
Classifier: License :: OSI Approved :: MIT License
Classifier: Programming Language :: Python :: 3
Classifier: Programming Language :: Python :: 3.10
Requires-Dist: tqdm (>=4.62.3,<5.0.0)
Project-URL: Repository, https://github.com/jmigual/slurmer
